secator/.gitignore
secator/__init__.py
secator/celery.py
secator/celery_signals.py
secator/celery_utils.py
secator/cli.py
secator/cli_helper.py
secator/click.py
secator/completion.py
secator/config.py
secator/cve.py
secator/decorators.py
secator/definitions.py
secator/installer.py
secator/loader.py
secator/report.py
secator/requests.py
secator/rich.py
secator/template.py
secator/thread.py
secator/tree.py
secator/utils.py
secator/utils_test.py
secator/configs/__init__.py
secator/configs/profiles/__init__.py
secator/configs/profiles/active.yaml
secator/configs/profiles/aggressive.yaml
secator/configs/profiles/all_ports.yaml
secator/configs/profiles/full.yaml
secator/configs/profiles/http_headless.yaml
secator/configs/profiles/http_record.yaml
secator/configs/profiles/insane.yaml
secator/configs/profiles/paranoid.yaml
secator/configs/profiles/passive.yaml
secator/configs/profiles/polite.yaml
secator/configs/profiles/sneaky.yaml
secator/configs/profiles/stealth.yaml
secator/configs/profiles/tor.yaml
secator/configs/scans/__init__.py
secator/configs/scans/domain.yaml
secator/configs/scans/host.yaml
secator/configs/scans/network.yaml
secator/configs/scans/subdomain.yaml
secator/configs/scans/url.yaml
secator/configs/workflows/__init__.py
secator/configs/workflows/cidr_recon.yaml
secator/configs/workflows/code_scan.yaml
secator/configs/workflows/domain_recon.yaml
secator/configs/workflows/host_recon.yaml
secator/configs/workflows/subdomain_recon.yaml
secator/configs/workflows/url_bypass.yaml
secator/configs/workflows/url_crawl.yaml
secator/configs/workflows/url_dirsearch.yaml
secator/configs/workflows/url_fuzz.yaml
secator/configs/workflows/url_params_fuzz.yaml
secator/configs/workflows/url_secrets_hunt.yaml
secator/configs/workflows/url_vuln.yaml
secator/configs/workflows/user_hunt.yaml
secator/configs/workflows/wordpress.yaml
secator/exporters/__init__.py
secator/exporters/_base.py
secator/exporters/console.py
secator/exporters/csv.py
secator/exporters/gdrive.py
secator-0.24.0.dist-info/METADATA
secator-0.24.0.dist-info/WHEEL
secator-0.24.0.dist-info/entry_points.txt
secator-0.24.0.dist-info/licenses/LICENSE
secator-0.24.0.dist-info/RECORD
