Metadata-Version: 2.4
Name: secator
Version: 0.24.0
Summary: The pentester's swiss knife.
Project-URL: Homepage, https://github.com/freelabz/secator
Project-URL: Issues, https://github.com/freelabz/secator/issues
Author-email: FreeLabz <sales@freelabz.com>
License-File: LICENSE
Keywords: automation,cybersecurity,pentest,recon,vulnerability
Classifier: Development Status :: 3 - Alpha
Classifier: Intended Audience :: Developers
Classifier: Intended Audience :: Information Technology
Classifier: License :: Free for non-commercial use
Classifier: Operating System :: Unix
Classifier: Programming Language :: Python
Classifier: Programming Language :: Python :: 3
Classifier: Programming Language :: Python :: 3.8
Classifier: Programming Language :: Python :: 3.9
Classifier: Programming Language :: Python :: 3.10
Classifier: Programming Language :: Python :: 3.11
Requires-Python: >=3.8
Requires-Dist: beautifulsoup4<=5
Requires-Dist: celery<6
Requires-Dist: click<8.2.0
Requires-Dist: cpe<2
Requires-Dist: distro<2
Requires-Dist: dnspython<3
Requires-Dist: dotmap<2
Requires-Dist: free-proxy<2
Requires-Dist: furl<3
Requires-Dist: greenlet<4
Requires-Dist: humanize<5
Requires-Dist: ifaddr<1
Requires-Dist: jinja2<4
Requires-Dist: packaging<25
Requires-Dist: psutil<7
Requires-Dist: pydantic<3
Requires-Dist: python-dotenv<2
Requires-Dist: pyyaml<7
Requires-Dist: requests<3
Requires-Dist: retry<1
Requires-Dist: rich-click<1.7
Requires-Dist: rich<14
Requires-Dist: tldextract<6
Requires-Dist: typing-extensions<5
Requires-Dist: validators<1
Requires-Dist: xmltodict<1
Provides-Extra: build
Requires-Dist: hatch<2; extra == 'build'
Provides-Extra: dev
Requires-Dist: asciinema-automation<1; extra == 'dev'
Requires-Dist: coverage<8; extra == 'dev'
Requires-Dist: flake8<8; extra == 'dev'
Requires-Dist: pytest<9; extra == 'dev'
Requires-Dist: watchdog<3; extra == 'dev'
Provides-Extra: gcs
Requires-Dist: google-cloud-storage<3; extra == 'gcs'
Provides-Extra: gdrive
Requires-Dist: google-api-python-client<3; extra == 'gdrive'
Requires-Dist: gspread<7; extra == 'gdrive'
Provides-Extra: mongodb
Requires-Dist: pymongo<5; extra == 'mongodb'
Provides-Extra: redis
Requires-Dist: redis<6; extra == 'redis'
Provides-Extra: trace
Requires-Dist: memray<2; extra == 'trace'
Requires-Dist: pyinstrument<5; extra == 'trace'
Provides-Extra: worker
Requires-Dist: eventlet<1; extra == 'worker'
Requires-Dist: flower<3; extra == 'worker'
